ragbits/document_search/__init__.py
ragbits/document_search/_main.py
ragbits/document_search/cli.py
ragbits/document_search/py.typed
ragbits/document_search/documents/__init__.py
ragbits/document_search/documents/document.py
ragbits/document_search/documents/element.py
ragbits/document_search/ingestion/__init__.py
ragbits/document_search/ingestion/enrichers/__init__.py
ragbits/document_search/ingestion/enrichers/base.py
ragbits/document_search/ingestion/enrichers/exceptions.py
ragbits/document_search/ingestion/enrichers/image.py
ragbits/document_search/ingestion/enrichers/router.py
ragbits/document_search/ingestion/parsers/__init__.py
ragbits/document_search/ingestion/parsers/base.py
ragbits/document_search/ingestion/parsers/docling.py
ragbits/document_search/ingestion/parsers/exceptions.py
ragbits/document_search/ingestion/parsers/router.py
ragbits/document_search/ingestion/parsers/unstructured.py
ragbits/document_search/ingestion/parsers/pptx/__init__.py
ragbits/document_search/ingestion/parsers/pptx/callbacks.py
ragbits/document_search/ingestion/parsers/pptx/exceptions.py
ragbits/document_search/ingestion/parsers/pptx/hyperlink_callback.py
ragbits/document_search/ingestion/parsers/pptx/metadata_callback.py
ragbits/document_search/ingestion/parsers/pptx/parser.py
ragbits/document_search/ingestion/parsers/pptx/speaker_notes_callback.py
ragbits/document_search/ingestion/strategies/__init__.py
ragbits/document_search/ingestion/strategies/base.py
ragbits/document_search/ingestion/strategies/batched.py
ragbits/document_search/ingestion/strategies/ray.py
ragbits/document_search/ingestion/strategies/sequential.py
ragbits/document_search/retrieval/__init__.py
ragbits/document_search/retrieval/rephrasers/__init__.py
ragbits/document_search/retrieval/rephrasers/base.py
ragbits/document_search/retrieval/rephrasers/llm.py
ragbits/document_search/retrieval/rephrasers/noop.py
ragbits/document_search/retrieval/rerankers/__init__.py
ragbits_document_search-1.3.0.dist-info/METADATA
ragbits_document_search-1.3.0.dist-info/WHEEL
ragbits_document_search-1.3.0.dist-info/RECORD
