Metadata-Version: 2.4
Name: ragbits-document-search
Version: 1.3.0
Summary: Document Search module for Ragbits
Project-URL: Homepage, https://github.com/deepsense-ai/ragbits
Project-URL: Bug Reports, https://github.com/deepsense-ai/ragbits/issues
Project-URL: Documentation, https://ragbits.deepsense.ai/
Project-URL: Source, https://github.com/deepsense-ai/ragbits
Author-email: "deepsense.ai" <ragbits@deepsense.ai>
License-Expression: MIT
Keywords: Document Search,GenAI,Generative AI,LLMs,Large Language Models,RAG,Retrieval Augmented Generation
Classifier: Development Status :: 4 - Beta
Classifier: Environment :: Console
Classifier: Intended Audience :: Science/Research
Classifier: License :: OSI Approved :: MIT License
Classifier: Natural Language :: English
Classifier: Operating System :: OS Independent
Classifier: Programming Language :: Python :: 3.10
Classifier: Programming Language :: Python :: 3.11
Classifier: Programming Language :: Python :: 3.12
Classifier: Programming Language :: Python :: 3.13
Classifier: Topic :: Scientific/Engineering :: Artificial Intelligence
Classifier: Topic :: Software Development :: Libraries :: Python Modules
Requires-Python: >=3.10
Requires-Dist: docling<3.0.0,>=2.15.1
Requires-Dist: filetype<2.0.0,>=1.2.0
Requires-Dist: opencv-python<5.0.0.0,>=4.11.0.86
Requires-Dist: python-pptx<2.0.0,>=1.0.0
Requires-Dist: ragbits-core==1.3.0
Requires-Dist: rerankers<1.0.0,>=0.6.1
Provides-Extra: ray
Requires-Dist: ray[data]<3.0.0,>=2.43.0; extra == 'ray'
Provides-Extra: unstructured
Requires-Dist: unstructured-client<1.0.0,>=0.26.0; extra == 'unstructured'
Requires-Dist: unstructured<1.0.0,>=0.16.9; extra == 'unstructured'
